{"version": 0.6, "generator": "Overpass API 0.7.59 e21c39fe", "osm3s": {"timestamp_osm_base": "2022-11-06T19:23:54Z", "copyright": "The data included in this document is from www.openstreetmap.org. The data is made available under ODbL."}, "elements": [{"type": "node", "id": 2924600186, "lat": 52.8509035, "lon": 7.0835378, "tags": {"fuel:diesel": "yes", "note": "Dieselzapfsaeule. Super an der Strassentankstelle (Kanister)", "seamark:small_craft_facility:category": "fuel_station", "seamark:type": "small_craft_facility", "waterway": "fuel"}}]}